{"cod": "200", "message": 0, "cnt": 40, "list": [{"dt": 1598713200, "main": {"temp": 299.97, "feels_like": 304.79, "temp_min": 299.78, "temp_max": 299.97, "pressure": 1005, "sea_level": 1006, "grnd_level": 1004, "humidity": 85, "temp_kf": 0.19}, "weather": [{"id": 501, "main": "Rain", "description": "moderate rain", "icon": "10n"}], "clouds": {"all": 95}, "wind": {"speed": 1.49, "deg": 261}, "visibility": 10000, "pop": 1, "rain": {"3h": 5.8}, "sys": {"pod": "n"}, "dt_txt": "2020-08-29 15:00:00"}, {"dt": 1598724000, "main": {"temp": 299.95, "feels_like": 303.26, "temp_min": 299.89, "temp_max": 299.95, "pressure": 1006, "sea_level": 1006, "grnd_level": 1004, "humidity": 84, "temp_kf": 0.06}, "weather": [{"id": 501, "main": "Rain", "description": "moderate rain", "icon": "10n"}], "clouds": {"all": 98}, "wind": {"speed": 3.47, "deg": 236}, "visibility": 10000, "pop": 1, "rain": {"3h": 3.6}, "sys": {"pod": "n"}, "dt_txt": "2020-08-29 18:00:00"}, {"dt": 1598734800, "main": {"temp": 299.71, "feels_like": 301.55, "temp_min": 299.68, "temp_max": 299.71, "pressure": 1004, "sea_level": 1004, "grnd_level": 1003, "humidity": 86, "temp_kf": 0.03}, "weather": [{"id": 501, "main": "Rain", "description": "moderate rain", "icon": "10n"}], "clouds": {"all": 98}, "wind": {"speed": 5.7, "deg": 227}, "visibility": 7414, "pop": 0.91, "rain": {"3h": 3.89}, "sys": {"pod": "n"}, "dt_txt": "2020-08-29 21:00:00"}, {"dt": 1598745600, "main": {"temp": 299.87, "feels_like": 301.48, "temp_min": 299.87, "temp_max": 299.87, "pressure": 1004, "sea_level": 1004, "grnd_level": 1003, "humidity": 86, "temp_kf": 0}, "weather": [{"id": 501, "main": "Rain", "description": "moderate rain", "icon": "10n"}], "clouds": {"all": 99}, "wind": {"speed": 6.16, "deg": 231}, "visibility": 7086, "pop": 0.95, "rain": {"3h": 5.13}, "sys": {"pod": "n"}, "dt_txt": "2020-08-30 00:00:00"}, {"dt": 1598756400, "main": {"temp": 300.29, "feels_like": 302.1, "temp_min": 300.29, "temp_max": 300.29, "pressure": 1007, "sea_level": 1007, "grnd_level": 1005, "humidity": 82, "temp_kf": 0}, "weather": [{"id": 501, "main": "Rain", "description": "moderate rain", "icon": "10d"}], "clouds": {"all": 100}, "wind": {"speed": 5.55, "deg": 212}, "visibility": 8403, "pop": 0.91, "rain": {"3h": 5.84}, "sys": {"pod": "d"}, "dt_txt": "2020-08-30 03:00:00"}, {"dt": 1598767200, "main": {"temp": 301.01, "feels_like": 302.28, "temp_min": 301.01, "temp_max": 301.01, "pressure": 1006, "sea_level": 1006, "grnd_level": 1004, "humidity": 80, "temp_kf": 0}, "weather": [{"id": 501, "main": "Rain", "description": "moderate rain", "icon": "10d"}], "clouds": {"all": 100}, "wind": {"speed": 6.57, "deg": 228}, "visibility": 6844, "pop": 1, "rain": {"3h": 5.18}, "sys": {"pod": "d"}, "dt_txt": "2020-08-30 06:00:00"}, {"dt": 1598778000, "main": {"temp": 301.27, "feels_like": 301.67, "temp_min": 301.27, "temp_max": 301.27, "pressure": 1005, "sea_level": 1005, "grnd_level": 1003, "humidity": 78, "temp_kf": 0}, "weather": [{"id": 501, "main": "Rain", "description": "moderate rain", "icon": "10d"}], "clouds": {"all": 100}, "wind": {"speed": 7.67, "deg": 239}, "visibility": 10000, "pop": 1, "rain": {"3h": 4.4}, "sys": {"pod": "d"}, "dt_txt": "2020-08-30 09:00:00"}, {"dt": 1598788800, "main": {"temp": 300.84, "feels_like": 301.4, "temp_min": 300.84, "temp_max": 300.84, "pressure": 1004, "sea_level": 1004, "grnd_level": 1003, "humidity": 82, "temp_kf": 0}, "weather": [{"id": 501, "main": "Rain", "description": "moderate rain", "icon": "10d"}], "clouds": {"all": 100}, "wind": {"speed": 7.79, "deg": 244}, "visibility": 6947, "pop": 1, "rain": {"3h": 5.08}, "sys": {"pod": "d"}, "dt_txt": "2020-08-30 12:00:00"}, {"dt": 1598799600, "main": {"temp": 300.59, "feels_like": 301.48, "temp_min": 300.59, "temp_max": 300.59, "pressure": 1006, "sea_level": 1006, "grnd_level": 1005, "humidity": 84, "temp_kf": 0}, "weather": [{"id": 501, "main": "Rain", "description": "moderate rain", "icon": "10n"}], "clouds": {"all": 100}, "wind": {"speed": 7.46, "deg": 238}, "visibility": 10000, "pop": 0.79, "rain": {"3h": 3.34}, "sys": {"pod": "n"}, "dt_txt": "2020-08-30 15:00:00"}, {"dt": 1598810400, "main": {"temp": 300.35, "feels_like": 301.73, "temp_min": 300.35, "temp_max": 300.35, "pressure": 1007, "sea_level": 1007, "grnd_level": 1005, "humidity": 85, "temp_kf": 0}, "weather": [{"id": 500, "main": "Rain", "description": "light rain", "icon": "10n"}], "clouds": {"all": 96}, "wind": {"speed": 6.73, "deg": 229}, "visibility": 10000, "pop": 0.76, "rain": {"3h": 0.69}, "sys": {"pod": "n"}, "dt_txt": "2020-08-30 18:00:00"}, {"dt": 1598821200, "main": {"temp": 300.27, "feels_like": 300.79, "temp_min": 300.27, "temp_max": 300.27, "pressure": 1005, "sea_level": 1005, "grnd_level": 1003, "humidity": 84, "temp_kf": 0}, "weather": [{"id": 500, "main": "Rain", "description": "light rain", "icon": "10n"}], "clouds": {"all": 27}, "wind": {"speed": 7.72, "deg": 231}, "visibility": 10000, "pop": 0.63, "rain": {"3h": 0.56}, "sys": {"pod": "n"}, "dt_txt": "2020-08-30 21:00:00"}, {"dt": 1598832000, "main": {"temp": 300.13, "feels_like": 300.45, "temp_min": 300.13, "temp_max": 300.13, "pressure": 1005, "sea_level": 1005, "grnd_level": 1003, "humidity": 82, "temp_kf": 0}, "weather": [{"id": 500, "main": "Rain", "description": "light rain", "icon": "10n"}], "clouds": {"all": 32}, "wind": {"speed": 7.55, "deg": 231}, "visibility": 10000, "pop": 1, "rain": {"3h": 1.44}, "sys": {"pod": "n"}, "dt_txt": "2020-08-31 00:00:00"}, {"dt": 1598842800, "main": {"temp": 300.48, "feels_like": 300.82, "temp_min": 300.48, "temp_max": 300.48, "pressure": 1007, "sea_level": 1007, "grnd_level": 1005, "humidity": 81, "temp_kf": 0}, "weather": [{"id": 501, "main": "Rain", "description": "moderate rain", "icon": "10d"}], "clouds": {"all": 11}, "wind": {"speed": 7.63, "deg": 227}, "visibility": 10000, "pop": 1, "rain": {"3h": 3.44}, "sys": {"pod": "d"}, "dt_txt": "2020-08-31 03:00:00"}, {"dt": 1598853600, "main": {"temp": 301.15, "feels_like": 301.7, "temp_min": 301.15, "temp_max": 301.15, "pressure": 1008, "sea_level": 1008, "grnd_level": 1006, "humidity": 78, "temp_kf": 0}, "weather": [{"id": 501, "main": "Rain", "description": "moderate rain", "icon": "10d"}], "clouds": {"all": 7}, "wind": {"speed": 7.36, "deg": 230}, "visibility": 10000, "pop": 1, "rain": {"3h": 4.54}, "sys": {"pod": "d"}, "dt_txt": "2020-08-31 06:00:00"}, {"dt": 1598864400, "main": {"temp": 301.46, "feels_like": 302.32, "temp_min": 301.46, "temp_max": 301.46, "pressure": 1006, "sea_level": 1006, "grnd_level": 1005, "humidity": 77, "temp_kf": 0}, "weather": [{"id": 500, "main": "Rain", "description": "light rain", "icon": "10d"}], "clouds": {"all": 2}, "wind": {"speed": 6.98, "deg": 241}, "visibility": 10000, "pop": 1, "rain": {"3h": 2.06}, "sys": {"pod": "d"}, "dt_txt": "2020-08-31 09:00:00"}, {"dt": 1598875200, "main": {"temp": 301.13, "feels_like": 303.31, "temp_min": 301.13, "temp_max": 301.13, "pressure": 1006, "sea_level": 1006, "grnd_level": 1004, "humidity": 80, "temp_kf": 0}, "weather": [{"id": 500, "main": "Rain", "description": "light rain", "icon": "10d"}], "clouds": {"all": 1}, "wind": {"speed": 5.37, "deg": 231}, "visibility": 10000, "pop": 1, "rain": {"3h": 0.86}, "sys": {"pod": "d"}, "dt_txt": "2020-08-31 12:00:00"}, {"dt": 1598886000, "main": {"temp": 300.63, "feels_like": 303.65, "temp_min": 300.63, "temp_max": 300.63, "pressure": 1008, "sea_level": 1008, "grnd_level": 1006, "humidity": 83, "temp_kf": 0}, "weather": [{"id": 500, "main": "Rain", "description": "light rain", "icon": "10n"}], "clouds": {"all": 0}, "wind": {"speed": 4.28, "deg": 224}, "visibility": 10000, "pop": 0.74, "rain": {"3h": 0.29}, "sys": {"pod": "n"}, "dt_txt": "2020-08-31 15:00:00"}, {"dt": 1598896800, "main": {"temp": 300.4, "feels_like": 303.53, "temp_min": 300.4, "temp_max": 300.4, "pressure": 1009, "sea_level": 1009, "grnd_level": 1007, "humidity": 84, "temp_kf": 0}, "weather": [{"id": 500, "main": "Rain", "description": "light rain", "icon": "10n"}], "clouds": {"all": 3}, "wind": {"speed": 4.1, "deg": 228}, "visibility": 10000, "pop": 0.92, "rain": {"3h": 0.89}, "sys": {"pod": "n"}, "dt_txt": "2020-08-31 18:00:00"}, {"dt": 1598907600, "main": {"temp": 300.16, "feels_like": 303.42, "temp_min": 300.16, "temp_max": 300.16, "pressure": 1007, "sea_level": 1007, "grnd_level": 1006, "humidity": 84, "temp_kf": 0}, "weather": [{"id": 500, "main": "Rain", "description": "light rain", "icon": "10n"}], "clouds": {"all": 16}, "wind": {"speed": 3.71, "deg": 236}, "visibility": 10000, "pop": 0.64, "rain": {"3h": 1.11}, "sys": {"pod": "n"}, "dt_txt": "2020-08-31 21:00:00"}, {"dt": 1598918400, "main": {"temp": 299.96, "feels_like": 303.75, "temp_min": 299.96, "temp_max": 299.96, "pressure": 1008, "sea_level": 1008, "grnd_level": 1006, "humidity": 84, "temp_kf": 0}, "weather": [{"id": 500, "main": "Rain", "description": "light rain", "icon": "10n"}], "clouds": {"all": 10}, "wind": {"speed": 2.79, "deg": 220}, "visibility": 10000, "pop": 0.58, "rain": {"3h": 0.76}, "sys": {"pod": "n"}, "dt_txt": "2020-09-01 00:00:00"}, {"dt": 1598929200, "main": {"temp": 300.13, "feels_like": 303.87, "temp_min": 300.13, "temp_max": 300.13, "pressure": 1009, "sea_level": 1009, "grnd_level": 1008, "humidity": 83, "temp_kf": 0}, "weather": [{"id": 500, "main": "Rain", "description": "light rain", "icon": "10d"}], "clouds": {"all": 0}, "wind": {"speed": 2.84, "deg": 179}, "visibility": 10000, "pop": 0.41, "rain": {"3h": 0.39}, "sys": {"pod": "d"}, "dt_txt": "2020-09-01 03:00:00"}, {"dt": 1598940000, "main": {"temp": 301.41, "feels_like": 304.43, "temp_min": 301.41, "temp_max": 301.41, "pressure": 1010, "sea_level": 1010, "grnd_level": 1008, "humidity": 79, "temp_kf": 0}, "weather": [{"id": 500, "main": "Rain", "description": "light rain", "icon": "10d"}], "clouds": {"all": 3}, "wind": {"speed": 4.21, "deg": 212}, "visibility": 10000, "pop": 0.52, "rain": {"3h": 0.58}, "sys": {"pod": "d"}, "dt_txt": "2020-09-01 06:00:00"}, {"dt": 1598950800, "main": {"temp": 301.64, "feels_like": 304.48, "temp_min": 301.64, "temp_max": 301.64, "pressure": 1008, "sea_level": 1008, "grnd_level": 1006, "humidity": 78, "temp_kf": 0}, "weather": [{"id": 500, "main": "Rain", "description": "light rain", "icon": "10d"}], "clouds": {"all": 3}, "wind": {"speed": 4.48, "deg": 220}, "visibility": 10000, "pop": 0.44, "rain": {"3h": 0.23}, "sys": {"pod": "d"}, "dt_txt": "2020-09-01 09:00:00"}, {"dt": 1598961600, "main": {"temp": 301.75, "feels_like": 304.86, "temp_min": 301.75, "temp_max": 301.75, "pressure": 1007, "sea_level": 1007, "grnd_level": 1005, "humidity": 79, "temp_kf": 0}, "weather": [{"id": 800, "main": "Clear", "description": "clear sky", "icon": "01d"}], "clouds": {"all": 4}, "wind": {"speed": 4.37, "deg": 249}, "visibility": 10000, "pop": 0.36, "sys": {"pod": "d"}, "dt_txt": "2020-09-01 12:00:00"}, {"dt": 1598972400, "main": {"temp": 301.1, "feels_like": 305.56, "temp_min": 301.1, "temp_max": 301.1, "pressure": 1009, "sea_level": 1009, "grnd_level": 1007, "humidity": 82, "temp_kf": 0}, "weather": [{"id": 803, "main": "Clouds", "description": "broken clouds", "icon": "04n"}], "clouds": {"all": 80}, "wind": {"speed": 2.43, "deg": 240}, "visibility": 10000, "pop": 0.25, "sys": {"pod": "n"}, "dt_txt": "2020-09-01 15:00:00"}, {"dt": 1598983200, "main": {"temp": 300.7, "feels_like": 305.63, "temp_min": 300.7, "temp_max": 300.7, "pressure": 1010, "sea_level": 1010, "grnd_level": 1008, "humidity": 83, "temp_kf": 0}, "weather": [{"id": 500, "main": "Rain", "description": "light rain", "icon": "10n"}], "clouds": {"all": 90}, "wind": {"speed": 1.61, "deg": 251}, "visibility": 10000, "pop": 0.29, "rain": {"3h": 0.23}, "sys": {"pod": "n"}, "dt_txt": "2020-09-01 18:00:00"}, {"dt": 1598994000, "main": {"temp": 300.23, "feels_like": 305.09, "temp_min": 300.23, "temp_max": 300.23, "pressure": 1008, "sea_level": 1008, "grnd_level": 1007, "humidity": 84, "temp_kf": 0}, "weather": [{"id": 500, "main": "Rain", "description": "light rain", "icon": "10n"}], "clouds": {"all": 100}, "wind": {"speed": 1.48, "deg": 273}, "visibility": 10000, "pop": 0.24, "rain": {"3h": 0.52}, "sys": {"pod": "n"}, "dt_txt": "2020-09-01 21:00:00"}, {"dt": 1599004800, "main": {"temp": 300, "feels_like": 305.5, "temp_min": 300, "temp_max": 300, "pressure": 1009, "sea_level": 1009, "grnd_level": 1007, "humidity": 82, "temp_kf": 0}, "weather": [{"id": 500, "main": "Rain", "description": "light rain", "icon": "10n"}], "clouds": {"all": 99}, "wind": {"speed": 0.05, "deg": 75}, "visibility": 10000, "pop": 0.24, "rain": {"3h": 0.37}, "sys": {"pod": "n"}, "dt_txt": "2020-09-02 00:00:00"}, {"dt": 1599015600, "main": {"temp": 300.16, "feels_like": 304.75, "temp_min": 300.16, "temp_max": 300.16, "pressure": 1010, "sea_level": 1010, "grnd_level": 1008, "humidity": 81, "temp_kf": 0}, "weather": [{"id": 804, "main": "Clouds", "description": "overcast clouds", "icon": "04d"}], "clouds": {"all": 100}, "wind": {"speed": 1.31, "deg": 123}, "visibility": 10000, "pop": 0, "sys": {"pod": "d"}, "dt_txt": "2020-09-02 03:00:00"}, {"dt": 1599026400, "main": {"temp": 301.13, "feels_like": 305.57, "temp_min": 301.13, "temp_max": 301.13, "pressure": 1011, "sea_level": 1011, "grnd_level": 1009, "humidity": 78, "temp_kf": 0}, "weather": [{"id": 804, "main": "Clouds", "description": "overcast clouds", "icon": "04d"}], "clouds": {"all": 100}, "wind": {"speed": 1.78, "deg": 192}, "visibility": 10000, "pop": 0, "sys": {"pod": "d"}, "dt_txt": "2020-09-02 06:00:00"}, {"dt": 1599037200, "main": {"temp": 301.68, "feels_like": 304.92, "temp_min": 301.68, "temp_max": 301.68, "pressure": 1008, "sea_level": 1008, "grnd_level": 1006, "humidity": 75, "temp_kf": 0}, "weather": [{"id": 804, "main": "Clouds", "description": "overcast clouds", "icon": "04d"}], "clouds": {"all": 100}, "wind": {"speed": 3.4, "deg": 244}, "visibility": 10000, "pop": 0.17, "sys": {"pod": "d"}, "dt_txt": "2020-09-02 09:00:00"}, {"dt": 1599048000, "main": {"temp": 301.76, "feels_like": 305.08, "temp_min": 301.76, "temp_max": 301.76, "pressure": 1007, "sea_level": 1007, "grnd_level": 1006, "humidity": 77, "temp_kf": 0}, "weather": [{"id": 500, "main": "Rain", "description": "light rain", "icon": "10d"}], "clouds": {"all": 100}, "wind": {"speed": 3.71, "deg": 286}, "visibility": 10000, "pop": 0.34, "rain": {"3h": 0.1}, "sys": {"pod": "d"}, "dt_txt": "2020-09-02 12:00:00"}, {"dt": 1599058800, "main": {"temp": 301.1, "feels_like": 305.24, "temp_min": 301.1, "temp_max": 301.1, "pressure": 1009, "sea_level": 1009, "grnd_level": 1007, "humidity": 81, "temp_kf": 0}, "weather": [{"id": 803, "main": "Clouds", "description": "broken clouds", "icon": "04n"}], "clouds": {"all": 78}, "wind": {"speed": 2.71, "deg": 300}, "visibility": 10000, "pop": 0.17, "sys": {"pod": "n"}, "dt_txt": "2020-09-02 15:00:00"}, {"dt": 1599069600, "main": {"temp": 300.82, "feels_like": 305.19, "temp_min": 300.82, "temp_max": 300.82, "pressure": 1010, "sea_level": 1010, "grnd_level": 1008, "humidity": 82, "temp_kf": 0}, "weather": [{"id": 803, "main": "Clouds", "description": "broken clouds", "icon": "04n"}], "clouds": {"all": 77}, "wind": {"speed": 2.33, "deg": 297}, "visibility": 10000, "pop": 0.1, "sys": {"pod": "n"}, "dt_txt": "2020-09-02 18:00:00"}, {"dt": 1599080400, "main": {"temp": 300.41, "feels_like": 305.03, "temp_min": 300.41, "temp_max": 300.41, "pressure": 1008, "sea_level": 1008, "grnd_level": 1006, "humidity": 83, "temp_kf": 0}, "weather": [{"id": 803, "main": "Clouds", "description": "broken clouds", "icon": "04n"}], "clouds": {"all": 57}, "wind": {"speed": 1.81, "deg": 308}, "visibility": 10000, "pop": 0, "sys": {"pod": "n"}, "dt_txt": "2020-09-02 21:00:00"}, {"dt": 1599091200, "main": {"temp": 300.11, "feels_like": 304.41, "temp_min": 300.11, "temp_max": 300.11, "pressure": 1008, "sea_level": 1008, "grnd_level": 1006, "humidity": 81, "temp_kf": 0}, "weather": [{"id": 802, "main": "Clouds", "description": "scattered clouds", "icon": "03n"}], "clouds": {"all": 46}, "wind": {"speed": 1.68, "deg": 4}, "visibility": 10000, "pop": 0, "sys": {"pod": "n"}, "dt_txt": "2020-09-03 00:00:00"}, {"dt": 1599102000, "main": {"temp": 300.5, "feels_like": 305.16, "temp_min": 300.5, "temp_max": 300.5, "pressure": 1010, "sea_level": 1010, "grnd_level": 1008, "humidity": 79, "temp_kf": 0}, "weather": [{"id": 802, "main": "Clouds", "description": "scattered clouds", "icon": "03d"}], "clouds": {"all": 32}, "wind": {"speed": 1.14, "deg": 41}, "visibility": 10000, "pop": 0, "sys": {"pod": "d"}, "dt_txt": "2020-09-03 03:00:00"}, {"dt": 1599112800, "main": {"temp": 301.62, "feels_like": 306.41, "temp_min": 301.62, "temp_max": 301.62, "pressure": 1009, "sea_level": 1009, "grnd_level": 1008, "humidity": 73, "temp_kf": 0}, "weather": [{"id": 803, "main": "Clouds", "description": "broken clouds", "icon": "04d"}], "clouds": {"all": 63}, "wind": {"speed": 0.77, "deg": 236}, "visibility": 10000, "pop": 0, "sys": {"pod": "d"}, "dt_txt": "2020-09-03 06:00:00"}, {"dt": 1599123600, "main": {"temp": 301.99, "feels_like": 304.58, "temp_min": 301.99, "temp_max": 301.99, "pressure": 1007, "sea_level": 1007, "grnd_level": 1005, "humidity": 73, "temp_kf": 0}, "weather": [{"id": 803, "main": "Clouds", "description": "broken clouds", "icon": "04d"}], "clouds": {"all": 77}, "wind": {"speed": 4.2, "deg": 285}, "visibility": 10000, "pop": 0.02, "sys": {"pod": "d"}, "dt_txt": "2020-09-03 09:00:00"}, {"dt": 1599134400, "main": {"temp": 301.87, "feels_like": 303.98, "temp_min": 301.87, "temp_max": 301.87, "pressure": 1006, "sea_level": 1006, "grnd_level": 1004, "humidity": 75, "temp_kf": 0}, "weather": [{"id": 803, "main": "Clouds", "description": "broken clouds", "icon": "04d"}], "clouds": {"all": 53}, "wind": {"speed": 5.16, "deg": 307}, "visibility": 10000, "pop": 0.02, "sys": {"pod": "d"}, "dt_txt": "2020-09-03 12:00:00"}], "city": {"id": 1275339, "name": "Mumbai", "coord": {"lat": 19.0144, "lon": 72.8479}, "country": "IN", "population": 1000000, "timezone": 19800, "sunrise": 1598662396, "sunset": 1598707571}}